mwjApiTest/__init__.py
mwjApiTest/manage.py
mwjApiTest/core/__init__.py
mwjApiTest/core/basecase.py
mwjApiTest/core/dataParser.py
mwjApiTest/core/db_client.py
mwjApiTest/core/env_prepare.py
mwjApiTest/core/generateCase.py
mwjApiTest/core/httptest.py
mwjApiTest/core/log_operation.py
mwjApiTest/core/make_data.py
mwjApiTest/core/send_report.py
mwjApiTest/core/testRunner.py
mwjApiTest/templates/__init__.py
mwjApiTest/templates/reports/__init__.py
mwjApiTest/templates/reports/dingtalk_templates.md
mwjApiTest/templates/reports/templates03.html
mwjApiTest/templates/reports/templates1.html
mwjApiTest/templates/reports/templates2.html
mwjApiTest/templates/reports/templates3.html
mwjApiTest/templates/request_file_demo/__init__.py
mwjApiTest/templates/request_file_demo/funcTools.py
mwjApiTest/templates/request_file_demo/run.py
mwjApiTest/templates/request_file_demo/settings.py
mwjApiTest/templates/request_file_demo/case_json/__init__.py
mwjApiTest/templates/request_file_demo/case_json/test_json_demo.json
mwjApiTest/templates/request_file_demo/case_py/__init__.py
mwjApiTest/templates/request_file_demo/case_py/test_case_demo.py
mwjApiTest/templates/request_file_demo/case_yaml/__init__.py
mwjApiTest/templates/request_file_demo/case_yaml/test_case_demo.yaml
mwjApiTest/templates/request_file_demo/logs/__init__.py
mwjApiTest/templates/request_file_demo/reports/__init__.py
mwjApiTest/utils/__init__.py
mwj_apitest-1.2.3.dist-info/LICENSE
mwj_apitest-1.2.3.dist-info/METADATA
mwj_apitest-1.2.3.dist-info/WHEEL
mwj_apitest-1.2.3.dist-info/entry_points.txt
mwj_apitest-1.2.3.dist-info/top_level.txt
mwj_apitest-1.2.3.dist-info/RECORD
