Metadata-Version: 2.1
Name: mwj-apitest
Version: 1.2.3
Summary: 无需编码的接口测试框架,目前支持json、yaml、py文件格式的用例,命令行mwj查看帮助。
Home-page: https://github.com/Lvan826199/mwjApiTest
Author: 梦无矶小仔
Author-email: Lvan826199@163.com
Classifier: Programming Language :: Python :: 3
Classifier: License :: OSI Approved :: MIT License
Classifier: Operating System :: OS Independent
Requires-Python: >=3.8
License-File: LICENSE
Requires-Dist: Faker (==18.10.1)
Requires-Dist: Jinja2 (==3.1.2)
Requires-Dist: jsonpath (==0.82)
Requires-Dist: PyMySQL (==1.0.2)
Requires-Dist: PyYAML (==6.0)
Requires-Dist: Requests (==2.31.0)
Requires-Dist: requests-toolbelt (==1.0.0)
Requires-Dist: rsa (==4.7.2)
Requires-Dist: colorama (==0.4.6)
Requires-Dist: colorlog (==6.7.0)
